flask_admin_elasticsearch_dsl/__init__.py
flask_admin_elasticsearch_dsl/forms.py
flask_admin_elasticsearch_dsl/views.py
flask_admin_elasticsearch_dsl-0.0.1.dist-info/DESCRIPTION.rst
flask_admin_elasticsearch_dsl-0.0.1.dist-info/METADATA
flask_admin_elasticsearch_dsl-0.0.1.dist-info/RECORD
flask_admin_elasticsearch_dsl-0.0.1.dist-info/WHEEL
flask_admin_elasticsearch_dsl-0.0.1.dist-info/metadata.json
flask_admin_elasticsearch_dsl-0.0.1.dist-info/top_level.txt
