Metadata-Version: 2.0
Name: flask-admin-elasticsearch-dsl
Version: 0.0.1
Summary: UNKNOWN
Home-page: https://github.com/p1c2u/flask-admin-elasticsearch-dsl
Author: Artur Maciąg
Author-email: maciag.artur@gmail.com
License: UNKNOWN
Platform: UNKNOWN
Classifier: Intended Audience :: Developers
Classifier: Programming Language :: Python :: 3.5
Classifier: Programming Language :: Python :: 3.6
Classifier: Topic :: Software Development :: Libraries
Requires-Dist: elasticsearch-dsl
Requires-Dist: flask-admin
Requires-Dist: wtforms
